{
  "schemaVersion": "1.0.0",
  "id": "cici",
  "name": "Cici",
  "releaseYear": 2023,
  "skillsVerified": false,
  "resourceType": "none",
  "damageType": "physical",
  "roles": [
    "Fighter"
  ],
  "specialties": [
    "Damage",
    "Regen"
  ],
  "maxLevel": 15,
  "baseStats": {
    "hp": {
      "base": 2431,
      "growth": 195
    },
    "hpRegen": {
      "base": 6,
      "growth": 0.5714
    },
    "mana": {
      "base": 0,
      "growth": 0
    },
    "manaRegen": {
      "base": 0,
      "growth": 0
    },
    "physicalAttack": {
      "base": 129,
      "growth": 6.93
    },
    "magicPower": {
      "base": 0,
      "growth": 0
    },
    "physicalDefense": {
      "base": 23,
      "growth": 4
    },
    "magicDefense": {
      "base": 15,
      "growth": 2.5
    },
    "attackSpeed": {
      "base": 1.07,
      "growth": 0.02
    },
    "attackSpeedRatio": 1,
    "movementSpeed": {
      "base": 250,
      "growth": 0
    },
    "critChance": {
      "base": 0,
      "growth": 0
    }
  },
  "skills": [
    {
      "slot": "passive",
      "name": "Performer's Delight",
      "maxLevel": 1,
      "algorithms": [
        {
          "id": "todo",
          "todo": "Author from wiki: https://mobile-legends.fandom.com/wiki/Cici",
          "outputs": []
        }
      ]
    },
    {
      "slot": "skill_1",
      "name": "Yo-Yo Blitz",
      "maxLevel": 6,
      "algorithms": [
        {
          "id": "todo",
          "todo": "Author from wiki: https://mobile-legends.fandom.com/wiki/Cici",
          "outputs": []
        }
      ]
    },
    {
      "slot": "skill_2",
      "name": "Buoyant Bounce",
      "maxLevel": 6,
      "algorithms": [
        {
          "id": "todo",
          "todo": "Author from wiki: https://mobile-legends.fandom.com/wiki/Cici",
          "outputs": []
        }
      ]
    },
    {
      "slot": "ultimate",
      "name": "Curtain Call",
      "maxLevel": 3,
      "algorithms": [
        {
          "id": "todo",
          "todo": "Author from wiki: https://mobile-legends.fandom.com/wiki/Cici",
          "outputs": []
        }
      ]
    }
  ],
  "sources": [
    {
      "field": "baseStats",
      "url": "https://mobile-legends.fandom.com/wiki/Cici",
      "retrieved": "2026-06-29"
    }
  ]
}
